[{"id": "0", "name": "CTOR_NOT_FOUND", "colorPrimary": "#D4D4D4", "colorSecondary": "#000000"}, {"id": "1", "name": "McLaren", "colorPrimary": "#F47600", "colorSecondary": "#000000"}, {"id": "2", "name": "BMW Sauber", "colorPrimary": "#FFFFFF", "colorSecondary": "#16588E"}, {"id": "3", "name": "Williams", "colorPrimary": "#1868DB", "colorSecondary": null}, {"id": "4", "name": "Renault", "colorPrimary": "#f7d747", "colorSecondary": "#000000"}, {"id": "5", "name": "Toro Rosso", "colorPrimary": "#00144A", "colorSecondary": "#EC0742"}, {"id": "6", "name": "Ferrari", "colorPrimary": "#EF1A2D", "colorSecondary": null}, {"id": "7", "name": "Toyota", "colorPrimary": "#EB0A1E", "colorSecondary": "#FFFFFF"}, {"id": "8", "name": "Super Aguri", "colorPrimary": "#FFFFFF", "colorSecondary": "#e20010"}, {"id": "9", "name": "Red Bull", "colorPrimary": "#121F45", "colorSecondary": "#FF004C"}, {"id": "10", "name": "Force India", "colorPrimary": "#00A85C", "colorSecondary": "#F27836"}, {"id": "11", "name": "Honda", "colorPrimary": "#FFFFFF", "colorSecondary": "#f30f34"}, {"id": "12", "name": "Spyker", "colorPrimary": "#F1C31E", "colorSecondary": "#C0C0C0"}, {"id": "13", "name": "MF1", "colorPrimary": "#ff0000", "colorSecondary": "#333333"}, {"id": "14", "name": "Spyker MF1", "colorPrimary": "#D4D4D4", "colorSecondary": null}, {"id": "15", "name": "Sauber", "colorPrimary": "#01C00E", "colorSecondary": null}, {"id": "16", "name": "BAR", "colorPrimary": "#F1C31E", "colorSecondary": "#C0C0C0"}, {"id": "17", "name": "Jordan", "colorPrimary": "#FFDD00", "colorSecondary": "#000000"}, {"id": "18", "name": "Minardi", "colorPrimary": "#FFFF00", "colorSecondary": null}, {"id": "19", "name": "Jaguar", "colorPrimary": "#004225", "colorSecondary": null}, {"id": "20", "name": "Prost", "colorPrimary": "#003B5C", "colorSecondary": null}, {"id": "21", "name": "Arrows", "colorPrimary": "#FF6600", "colorSecondary": "#FF6600"}, {"id": "22", "name": "Benetton", "colorPrimary": "#008860", "colorSecondary": null}, {"id": "23", "name": "Brawn", "colorPrimary": "#FFFFFF", "colorSecondary": "#D1E200"}, {"id": "24", "name": "Stewart", "colorPrimary": "#FFFFFF", "colorSecondary": "#2F4198"}, {"id": "25", "name": "Tyrrell", "colorPrimary": "#D4D4D4", "colorSecondary": null}, {"id": "26", "name": "Lola", "colorPrimary": "#D4D4D4", "colorSecondary": null}, {"id": "27", "name": "Ligier", "colorPrimary": "#D4D4D4", "colorSecondary": null}, {"id": "28", "name": "Forti", "colorPrimary": "#D4D4D4", "colorSecondary": null}, {"id": "29", "name": "Footwork", "colorPrimary": "#D4D4D4", "colorSecondary": null}, {"id": "30", "name": "Pacific", "colorPrimary": "#D4D4D4", "colorSecondary": null}, {"id": "31", "name": "Simtek", "colorPrimary": "#D4D4D4", "colorSecondary": null}, {"id": "32", "name": "Team Lotus", "colorPrimary": "#D4D4D4", "colorSecondary": null}, {"id": "33", "name": "Larrousse", "colorPrimary": "#D4D4D4", "colorSecondary": null}, {"id": "34", "name": "Brabham", "colorPrimary": "#D4D4D4", "colorSecondary": null}, {"id": "35", "name": "Dallara", "colorPrimary": "#D4D4D4", "colorSecondary": null}, {"id": "36", "name": "Fondmetal", "colorPrimary": "#D4D4D4", "colorSecondary": null}, {"id": "37", "name": "March", "colorPrimary": "#D4D4D4", "colorSecondary": null}, {"id": "38", "name": "Andrea Moda", "colorPrimary": "#D4D4D4", "colorSecondary": null}, {"id": "39", "name": "AGS", "colorPrimary": "#D4D4D4", "colorSecondary": null}, {"id": "40", "name": "Lambo", "colorPrimary": "#D4D4D4", "colorSecondary": null}, {"id": "41", "name": "Leyton House", "colorPrimary": "#D4D4D4", "colorSecondary": null}, {"id": "42", "name": "Coloni", "colorPrimary": "#D4D4D4", "colorSecondary": null}, {"id": "44", "name": "Euro Brun", "colorPrimary": "#D4D4D4", "colorSecondary": null}, {"id": "45", "name": "Osella", "colorPrimary": "#D4D4D4", "colorSecondary": null}, {"id": "46", "name": "Onyx", "colorPrimary": "#D4D4D4", "colorSecondary": null}, {"id": "47", "name": "Life", "colorPrimary": "#D4D4D4", "colorSecondary": null}, {"id": "48", "name": "Rial", "colorPrimary": "#D4D4D4", "colorSecondary": null}, {"id": "49", "name": "Zakspeed", "colorPrimary": "#D4D4D4", "colorSecondary": null}, {"id": "50", "name": "RAM", "colorPrimary": "#D4D4D4", "colorSecondary": null}, {"id": "51", "name": "Alfa Romeo", "colorPrimary": "#D4D4D4", "colorSecondary": null}, {"id": "52", "name": "Spirit", "colorPrimary": "#D4D4D4", "colorSecondary": null}, {"id": "53", "name": "Toleman", "colorPrimary": "#D4D4D4", "colorSecondary": null}, {"id": "54", "name": "ATS", "colorPrimary": "#D4D4D4", "colorSecondary": null}, {"id": "55", "name": "Theodore", "colorPrimary": "#D4D4D4", "colorSecondary": null}, {"id": "56", "name": "Fittipaldi", "colorPrimary": "#D4D4D4", "colorSecondary": null}, {"id": "57", "name": "Ensign", "colorPrimary": "#D4D4D4", "colorSecondary": null}, {"id": "58", "name": "Shadow", "colorPrimary": "#D4D4D4", "colorSecondary": null}, {"id": "59", "name": "Wolf", "colorPrimary": "#D4D4D4", "colorSecondary": null}, {"id": "60", "name": "Merzario", "colorPrimary": "#D4D4D4", "colorSecondary": null}, {"id": "61", "name": "Kauhsen", "colorPrimary": "#D4D4D4", "colorSecondary": null}, {"id": "62", "name": "Rebaque", "colorPrimary": "#D4D4D4", "colorSecondary": null}, {"id": "63", "name": "Surtees", "colorPrimary": "#D4D4D4", "colorSecondary": null}, {"id": "64", "name": "Hesketh", "colorPrimary": "#D4D4D4", "colorSecondary": null}, {"id": "65", "name": "Martini", "colorPrimary": "#D4D4D4", "colorSecondary": null}, {"id": "66", "name": "BRM", "colorPrimary": "#D4D4D4", "colorSecondary": null}, {"id": "67", "name": "Penske", "colorPrimary": "#D4D4D4", "colorSecondary": null}, {"id": "68", "name": "LEC", "colorPrimary": "#D4D4D4", "colorSecondary": null}, {"id": "69", "name": "McGuire", "colorPrimary": "#D4D4D4", "colorSecondary": null}, {"id": "70", "name": "Boro", "colorPrimary": "#D4D4D4", "colorSecondary": null}, {"id": "71", "name": "Apollon", "colorPrimary": "#D4D4D4", "colorSecondary": null}, {"id": "72", "name": "Kojima", "colorPrimary": "#D4D4D4", "colorSecondary": null}, {"id": "73", "name": "Parnelli", "colorPrimary": "#D4D4D4", "colorSecondary": null}, {"id": "74", "name": "Maki", "colorPrimary": "#D4D4D4", "colorSecondary": null}, {"id": "75", "name": "Embassy Hill", "colorPrimary": "#D4D4D4", "colorSecondary": null}, {"id": "76", "name": "Lyncar", "colorPrimary": "#D4D4D4", "colorSecondary": null}, {"id": "77", "name": "Trojan", "colorPrimary": "#D4D4D4", "colorSecondary": null}, {"id": "78", "name": "Amon", "colorPrimary": "#D4D4D4", "colorSecondary": null}, {"id": "79", "name": "Token", "colorPrimary": "#D4D4D4", "colorSecondary": null}, {"id": "80", "name": "Iso Marlboro", "colorPrimary": "#D4D4D4", "colorSecondary": null}, {"id": "81", "name": "Tecno", "colorPrimary": "#D4D4D4", "colorSecondary": null}, {"id": "82", "name": "Matra", "colorPrimary": "#D4D4D4", "colorSecondary": null}, {"id": "83", "name": "Politoys", "colorPrimary": "#D4D4D4", "colorSecondary": null}, {"id": "84", "name": "Connew", "colorPrimary": "#D4D4D4", "colorSecondary": null}, {"id": "85", "name": "Bellasi", "colorPrimary": "#D4D4D4", "colorSecondary": null}, {"id": "86", "name": "De Tomaso", "colorPrimary": "#D4D4D4", "colorSecondary": null}, {"id": "87", "name": "Cooper", "colorPrimary": "#D4D4D4", "colorSecondary": null}, {"id": "88", "name": "Eagle", "colorPrimary": "#D4D4D4", "colorSecondary": null}, {"id": "89", "name": "LDS", "colorPrimary": "#D4D4D4", "colorSecondary": null}, {"id": "90", "name": "Protos", "colorPrimary": "#D4D4D4", "colorSecondary": null}, {"id": "91", "name": "Shannon", "colorPrimary": "#D4D4D4", "colorSecondary": null}, {"id": "92", "name": "Scirocco", "colorPrimary": "#D4D4D4", "colorSecondary": null}, {"id": "93", "name": "RE", "colorPrimary": "#D4D4D4", "colorSecondary": null}, {"id": "94", "name": "BRP", "colorPrimary": "#D4D4D4", "colorSecondary": null}, {"id": "95", "name": "Porsche", "colorPrimary": "#D4D4D4", "colorSecondary": null}, {"id": "96", "name": "Derrington", "colorPrimary": "#D4D4D4", "colorSecondary": null}, {"id": "97", "name": "Gilby", "colorPrimary": "#D4D4D4", "colorSecondary": null}, {"id": "98", "name": "Stebro", "colorPrimary": "#D4D4D4", "colorSecondary": null}, {"id": "99", "name": "Emeryson", "colorPrimary": "#D4D4D4", "colorSecondary": null}, {"id": "100", "name": "ENB", "colorPrimary": "#D4D4D4", "colorSecondary": null}, {"id": "101", "name": "JBW", "colorPrimary": "#D4D4D4", "colorSecondary": null}, {"id": "102", "name": "Ferguson", "colorPrimary": "#D4D4D4", "colorSecondary": null}, {"id": "103", "name": "MBM", "colorPrimary": "#D4D4D4", "colorSecondary": null}, {"id": "104", "name": "Behra-Porsche", "colorPrimary": "#D4D4D4", "colorSecondary": null}, {"id": "105", "name": "Maserati", "colorPrimary": "#D4D4D4", "colorSecondary": null}, {"id": "106", "name": "Scarab", "colorPrimary": "#D4D4D4", "colorSecondary": null}, {"id": "107", "name": "Watson", "colorPrimary": "#D4D4D4", "colorSecondary": null}, {"id": "108", "name": "Epperly", "colorPrimary": "#D4D4D4", "colorSecondary": null}, {"id": "109", "name": "Phillips", "colorPrimary": "#D4D4D4", "colorSecondary": null}, {"id": "110", "name": "Lesovsky", "colorPrimary": "#D4D4D4", "colorSecondary": null}, {"id": "111", "name": "Trevis", "colorPrimary": "#D4D4D4", "colorSecondary": null}, {"id": "112", "name": "Meskowski", "colorPrimary": "#D4D4D4", "colorSecondary": null}, {"id": "113", "name": "Kurtis Kraft", "colorPrimary": "#D4D4D4", "colorSecondary": null}, {"id": "114", "name": "Kuzma", "colorPrimary": "#D4D4D4", "colorSecondary": null}, {"id": "115", "name": "Christensen", "colorPrimary": "#D4D4D4", "colorSecondary": null}, {"id": "116", "name": "Ewing", "colorPrimary": "#D4D4D4", "colorSecondary": null}, {"id": "117", "name": "Aston Martin", "colorPrimary": "#229971", "colorSecondary": null}, {"id": "118", "name": "Vanwall", "colorPrimary": "#D4D4D4", "colorSecondary": null}, {"id": "119", "name": "Moore", "colorPrimary": "#D4D4D4", "colorSecondary": null}, {"id": "120", "name": "Dunn", "colorPrimary": "#D4D4D4", "colorSecondary": null}, {"id": "121", "name": "Elder", "colorPrimary": "#D4D4D4", "colorSecondary": null}, {"id": "122", "name": "Sutton", "colorPrimary": "#D4D4D4", "colorSecondary": null}, {"id": "123", "name": "Fry", "colorPrimary": "#D4D4D4", "colorSecondary": null}, {"id": "124", "name": "Tec-Mec", "colorPrimary": "#D4D4D4", "colorSecondary": null}, {"id": "125", "name": "Connaught", "colorPrimary": "#D4D4D4", "colorSecondary": null}, {"id": "126", "name": "Alta", "colorPrimary": "#D4D4D4", "colorSecondary": null}, {"id": "127", "name": "OSCA", "colorPrimary": "#D4D4D4", "colorSecondary": null}, {"id": "128", "name": "Gordini", "colorPrimary": "#D4D4D4", "colorSecondary": null}, {"id": "129", "name": "Stevens", "colorPrimary": "#D4D4D4", "colorSecondary": null}, {"id": "130", "name": "Bugatti", "colorPrimary": "#D4D4D4", "colorSecondary": null}, {"id": "131", "name": "Mercedes", "colorPrimary": "#00D7B6", "colorSecondary": "#C6C6C6"}, {"id": "132", "name": "Lancia", "colorPrimary": "#D4D4D4", "colorSecondary": null}, {"id": "133", "name": "HWM", "colorPrimary": "#D4D4D4", "colorSecondary": null}, {"id": "134", "name": "Schroeder", "colorPrimary": "#D4D4D4", "colorSecondary": null}, {"id": "135", "name": "Pawl", "colorPrimary": "#D4D4D4", "colorSecondary": null}, {"id": "136", "name": "Pankratz", "colorPrimary": "#D4D4D4", "colorSecondary": null}, {"id": "137", "name": "Arzani-Volpini", "colorPrimary": "#D4D4D4", "colorSecondary": null}, {"id": "138", "name": "Nichels", "colorPrimary": "#D4D4D4", "colorSecondary": null}, {"id": "139", "name": "Bromme", "colorPrimary": "#D4D4D4", "colorSecondary": null}, {"id": "140", "name": "Klenk", "colorPrimary": "#D4D4D4", "colorSecondary": null}, {"id": "141", "name": "Simca", "colorPrimary": "#D4D4D4", "colorSecondary": null}, {"id": "142", "name": "Turner", "colorPrimary": "#D4D4D4", "colorSecondary": null}, {"id": "143", "name": "Del Roy", "colorPrimary": "#D4D4D4", "colorSecondary": null}, {"id": "144", "name": "Veritas", "colorPrimary": "#D4D4D4", "colorSecondary": null}, {"id": "145", "name": "BMW", "colorPrimary": "#D4D4D4", "colorSecondary": null}, {"id": "146", "name": "EMW", "colorPrimary": "#D4D4D4", "colorSecondary": null}, {"id": "147", "name": "AFM", "colorPrimary": "#D4D4D4", "colorSecondary": null}, {"id": "148", "name": "Frazer Nash", "colorPrimary": "#D4D4D4", "colorSecondary": null}, {"id": "149", "name": "Sherman", "colorPrimary": "#D4D4D4", "colorSecondary": null}, {"id": "150", "name": "Deidt", "colorPrimary": "#D4D4D4", "colorSecondary": null}, {"id": "151", "name": "ERA", "colorPrimary": "#D4D4D4", "colorSecondary": null}, {"id": "152", "name": "Aston Butterworth", "colorPrimary": "#D4D4D4", "colorSecondary": null}, {"id": "153", "name": "Cisitalia", "colorPrimary": "#D4D4D4", "colorSecondary": null}, {"id": "154", "name": "Talbot-Lago", "colorPrimary": "#D4D4D4", "colorSecondary": null}, {"id": "155", "name": "Hall", "colorPrimary": "#D4D4D4", "colorSecondary": null}, {"id": "156", "name": "Marchese", "colorPrimary": "#D4D4D4", "colorSecondary": null}, {"id": "157", "name": "Langley", "colorPrimary": "#D4D4D4", "colorSecondary": null}, {"id": "158", "name": "Rae", "colorPrimary": "#D4D4D4", "colorSecondary": null}, {"id": "159", "name": "Olson", "colorPrimary": "#D4D4D4", "colorSecondary": null}, {"id": "160", "name": "Wetteroth", "colorPrimary": "#D4D4D4", "colorSecondary": null}, {"id": "161", "name": "Adams", "colorPrimary": "#D4D4D4", "colorSecondary": null}, {"id": "162", "name": "Snowberger", "colorPrimary": "#D4D4D4", "colorSecondary": null}, {"id": "163", "name": "Milano", "colorPrimary": "#D4D4D4", "colorSecondary": null}, {"id": "164", "name": "HRT", "colorPrimary": "#D4D4D4", "colorSecondary": null}, {"id": "167", "name": "Cooper-Maserati", "colorPrimary": "#D4D4D4", "colorSecondary": null}, {"id": "166", "name": "Virgin", "colorPrimary": "#D4D4D4", "colorSecondary": null}, {"id": "168", "name": "Cooper-OSCA", "colorPrimary": "#D4D4D4", "colorSecondary": null}, {"id": "169", "name": "Cooper-Borgward", "colorPrimary": "#D4D4D4", "colorSecondary": null}, {"id": "170", "name": "Cooper-Climax", "colorPrimary": "#D4D4D4", "colorSecondary": null}, {"id": "171", "name": "Cooper-Castellotti", "colorPrimary": "#D4D4D4", "colorSecondary": null}, {"id": "172", "name": "Lotus-Climax", "colorPrimary": "#D4D4D4", "colorSecondary": null}, {"id": "173", "name": "Lotus-Maserati", "colorPrimary": "#D4D4D4", "colorSecondary": null}, {"id": "174", "name": "De Tomaso-Osca", "colorPrimary": "#D4D4D4", "colorSecondary": null}, {"id": "175", "name": "De Tomaso-Alfa Romeo", "colorPrimary": "#D4D4D4", "colorSecondary": null}, {"id": "176", "name": "Lotus-BRM", "colorPrimary": "#D4D4D4", "colorSecondary": null}, {"id": "177", "name": "Lotus-Borgward", "colorPrimary": "#D4D4D4", "colorSecondary": null}, {"id": "178", "name": "Cooper-Alfa Romeo", "colorPrimary": "#D4D4D4", "colorSecondary": null}, {"id": "179", "name": "De Tomaso-Ferrari", "colorPrimary": "#D4D4D4", "colorSecondary": null}, {"id": "180", "name": "Lotus-Ford", "colorPrimary": "#D4D4D4", "colorSecondary": null}, {"id": "181", "name": "Brabham-BRM", "colorPrimary": "#D4D4D4", "colorSecondary": null}, {"id": "182", "name": "Brabham-Ford", "colorPrimary": "#D4D4D4", "colorSecondary": null}, {"id": "183", "name": "Brabham-Climax", "colorPrimary": "#D4D4D4", "colorSecondary": null}, {"id": "184", "name": "LDS-Climax", "colorPrimary": "#D4D4D4", "colorSecondary": null}, {"id": "185", "name": "LDS-Alfa Romeo", "colorPrimary": "#D4D4D4", "colorSecondary": null}, {"id": "186", "name": "Cooper-Ford", "colorPrimary": "#D4D4D4", "colorSecondary": null}, {"id": "187", "name": "McLaren-Ford", "colorPrimary": "#D4D4D4", "colorSecondary": null}, {"id": "188", "name": "McLaren-Serenissima", "colorPrimary": "#D4D4D4", "colorSecondary": null}, {"id": "189", "name": "Eagle-Climax", "colorPrimary": "#D4D4D4", "colorSecondary": null}, {"id": "190", "name": "Eagle-Weslake", "colorPrimary": "#D4D4D4", "colorSecondary": null}, {"id": "191", "name": "Brabham-Repco", "colorPrimary": "#D4D4D4", "colorSecondary": null}, {"id": "192", "name": "Cooper-Ferrari", "colorPrimary": "#D4D4D4", "colorSecondary": null}, {"id": "193", "name": "Cooper-ATS", "colorPrimary": "#D4D4D4", "colorSecondary": null}, {"id": "194", "name": "McLaren-BRM", "colorPrimary": "#D4D4D4", "colorSecondary": null}, {"id": "195", "name": "Cooper-BRM", "colorPrimary": "#D4D4D4", "colorSecondary": null}, {"id": "196", "name": "Matra-Ford", "colorPrimary": "#D4D4D4", "colorSecondary": null}, {"id": "197", "name": "BRM-Ford", "colorPrimary": "#D4D4D4", "colorSecondary": null}, {"id": "198", "name": "McLaren-Alfa Romeo", "colorPrimary": "#D4D4D4", "colorSecondary": null}, {"id": "199", "name": "March-Alfa Romeo", "colorPrimary": "#D4D4D4", "colorSecondary": null}, {"id": "200", "name": "March-Ford", "colorPrimary": "#D4D4D4", "colorSecondary": null}, {"id": "201", "name": "Lotus-Pratt &amp; Whitney", "colorPrimary": "#D4D4D4", "colorSecondary": null}, {"id": "202", "name": "Shadow-Ford", "colorPrimary": "#D4D4D4", "colorSecondary": null}, {"id": "203", "name": "Shadow-Matra", "colorPrimary": "#D4D4D4", "colorSecondary": null}, {"id": "204", "name": "Brabham-Alfa Romeo", "colorPrimary": "#D4D4D4", "colorSecondary": null}, {"id": "205", "name": "Lotus", "colorPrimary": "#D4D4D4", "colorSecondary": null}, {"id": "206", "name": "Marussia", "colorPrimary": "#D4D4D4", "colorSecondary": null}, {"id": "207", "name": "Caterham", "colorPrimary": "#D4D4D4", "colorSecondary": null}, {"id": "208", "name": "Lotus F1", "colorPrimary": "#D4D4D4", "colorSecondary": null}, {"id": "209", "name": "Manor Marussia", "colorPrimary": "#D4D4D4", "colorSecondary": null}, {"id": "210", "name": "Haas F1 Team", "colorPrimary": "#9C9FA2", "colorSecondary": null}, {"id": "211", "name": "Racing Point", "colorPrimary": "#D4D4D4", "colorSecondary": null}, {"id": "213", "name": "AlphaTauri", "colorPrimary": "#D4D4D4", "colorSecondary": null}, {"id": "214", "name": "Alpine F1 Team", "colorPrimary": "#00A1E8", "colorSecondary": null}, {"id": "215", "name": "RB F1 Team", "colorPrimary": "#6C98FF", "colorSecondary": null}]